dnevnik4python/__init__.py
dnevnik4python/dnevnikru.py
dnevnik4python/exceptions.py
dnevnik4python-0.0.11.dist-info/LICENSE
dnevnik4python-0.0.11.dist-info/WHEEL
dnevnik4python-0.0.11.dist-info/METADATA
dnevnik4python-0.0.11.dist-info/RECORD
