Metadata-Version: 2.1
Name: dnevnik4python
Version: 0.0.11
Summary: 
Author: hrog-zip
Author-email: 65674012+hrog-zip@users.noreply.github.com
Requires-Python: >=3.7,<4.0
Classifier: Programming Language :: Python :: 3
Classifier: Programming Language :: Python :: 3.10
Classifier: Programming Language :: Python :: 3.7
Classifier: Programming Language :: Python :: 3.8
Classifier: Programming Language :: Python :: 3.9
Requires-Dist: bs4 (>=0.0.1,<0.0.2)
Requires-Dist: fake-useragent (>=0.1.11,<0.2.0)
Requires-Dist: lxml (>=4.8.0,<5.0.0)
Requires-Dist: pytz (>=2022.1,<2023.0)
Requires-Dist: requests (>=2.27.1,<3.0.0)
